pullback_new_exp_forex_next3
