Metadata-Version: 1.0
Name: pullback-new-exp-forex-next3
Version: 1.5
Summary: pullback_new_exp_forex_next3
Home-page: UNKNOWN
Author: omid
Author-email: UNKNOWN
License: UNKNOWN
Platform: UNKNOWN
